src/__init__.py
src/checker.py
src/convertor.py
src/main.py
src/winOffeceInstaller.py
ml_convertor_free-0.1.14.dist-info/METADATA
ml_convertor_free-0.1.14.dist-info/WHEEL
ml_convertor_free-0.1.14.dist-info/entry_points.txt
ml_convertor_free-0.1.14.dist-info/top_level.txt
ml_convertor_free-0.1.14.dist-info/RECORD
