Metadata-Version: 2.1
Name: ml_convertor_free
Version: 0.1.14
Summary: MS Office va LibreOffice uchun konvertatsiya vositasi
Author: Bobomalikov Abduaziz
Author-email: Abduaziz7071@gmail.com
Requires-Dist: pywin32 ; platform_system == "Windows"
